LICENSE.txt
MANIFEST.in
setup.cfg
setup.py
django_surround.egg-info/PKG-INFO
django_surround.egg-info/SOURCES.txt
django_surround.egg-info/dependency_links.txt
django_surround.egg-info/pbr.json
django_surround.egg-info/requires.txt
django_surround.egg-info/top_level.txt
surround/__init__.py
surround/common/__init__.py
surround/common/git_info.py
surround/django/__init__.py
surround/django/apps.py
surround/django/context_cache.py
surround/django/decorators.py
surround/django/execution.py
surround/django/logging.py
surround/django/models.py
surround/django/redis.py
surround/django/sentry.py
surround/django/utils.py
surround/django/views.py
surround/django/basic/__init__.py
surround/django/basic/admin.py
surround/django/basic/invalid_subdomain_urls.py
surround/django/basic/templatetags/__init__.py
surround/django/basic/templatetags/common_ext.py
surround/django/coroutine/__init__.py
surround/django/coroutine/simple.py
surround/django/esi/__init__.py
surround/django/esi/simple.py
surround/django/health/__init__.py
surround/django/health/conf.py
surround/django/health/models.py
surround/django/health/utils.py
surround/django/health/views.py
surround/django/health/backends/__init__.py
surround/django/health/backends/base.py
surround/django/health/backends/cache.py
surround/django/health/backends/composite.py
surround/django/health/backends/constant.py
surround/django/local_orm/__init__.py
surround/django/local_orm/models.py
surround/django/local_orm/utils.py
surround/django/middleware/__init__.py
surround/django/middleware/minify_html.py
surround/django/platform_cache/__init__.py
surround/django/platform_cache/keys.py
surround/django/platform_cache/simple.py
surround/django/settings/__init__.py
surround/django/simple_cors/__init__.py
surround/django/simple_cors/decorators.py
surround/django/simple_cors/headers.py