Metadata-Version: 1.1
Name: django-surround
Version: 1.0.0
Summary: Library of useful utilities surrounding Django
Home-page: https://github.com/sniegu/django-surround
Author: Piotr Śniegowski
Author-email: piotr.sniegowski@gmail.com
License: MIT
Keywords: django,utilities
Platform: UNKNOWN
Classifier: Environment :: Web Environment
Classifier: Framework :: Django
Classifier: Intended Audience :: Developers
Classifier: Programming Language :: Python :: 2.7
Requires: Django
